odoo/addons/stock_picking_product_assortment/README.rst
odoo/addons/stock_picking_product_assortment/__init__.py
odoo/addons/stock_picking_product_assortment/__manifest__.py
odoo/addons/stock_picking_product_assortment/i18n/es.po
odoo/addons/stock_picking_product_assortment/i18n/stock_picking_product_assortment.pot
odoo/addons/stock_picking_product_assortment/models/__init__.py
odoo/addons/stock_picking_product_assortment/models/stock_move.py
odoo/addons/stock_picking_product_assortment/models/stock_move_line.py
odoo/addons/stock_picking_product_assortment/models/stock_picking.py
odoo/addons/stock_picking_product_assortment/readme/CONFIGURE.rst
odoo/addons/stock_picking_product_assortment/readme/CONTRIBUTORS.rst
odoo/addons/stock_picking_product_assortment/readme/DESCRIPTION.rst
odoo/addons/stock_picking_product_assortment/readme/ROADMAP.rst
odoo/addons/stock_picking_product_assortment/readme/USAGE.rst
odoo/addons/stock_picking_product_assortment/static/description/icon.png
odoo/addons/stock_picking_product_assortment/static/description/index.html
odoo/addons/stock_picking_product_assortment/tests/__init__.py
odoo/addons/stock_picking_product_assortment/tests/test_stock_picking_product_assortment.py
odoo/addons/stock_picking_product_assortment/views/stock_picking_view.xml
odoo13_addon_stock_picking_product_assortment-13.0.1.0.1.dev4.dist-info/METADATA
odoo13_addon_stock_picking_product_assortment-13.0.1.0.1.dev4.dist-info/WHEEL
odoo13_addon_stock_picking_product_assortment-13.0.1.0.1.dev4.dist-info/top_level.txt
odoo13_addon_stock_picking_product_assortment-13.0.1.0.1.dev4.dist-info/RECORD
